gblend/__init__.py
gblend/geometry.py
gblend/levels.py
gblend/variables.py
gblend/version.py
geometry_blender-0.0.5.dist-info/LICENSE
geometry_blender-0.0.5.dist-info/METADATA
geometry_blender-0.0.5.dist-info/WHEEL
geometry_blender-0.0.5.dist-info/top_level.txt
geometry_blender-0.0.5.dist-info/RECORD
