Metadata-Version: 2.1
Name: geometry-blender
Version: 0.0.5
Summary: Blending curves and surfaces
Home-page: https://github.com/valerocar/geometry-blender
Author: Carlos Valero
Author-email: valerocar@gmail.com
License: UNKNOWN
Platform: UNKNOWN
Classifier: Programming Language :: Python :: 3
Classifier: License :: OSI Approved :: MIT License
Classifier: Operating System :: OS Independent
Requires-Python: >=3.6
